npc_engine_import_wizard/__init__.py
npc_engine_import_wizard/cli.py
npc_engine_import_wizard/version.py
npc_engine_import_wizard/import_wizards/__init__.py
npc_engine_import_wizard/import_wizards/base_hf_import_wizard.py
npc_engine_import_wizard/import_wizards/base_import_wizard.py
npc_engine_import_wizard/import_wizards/espnet_import_wizard.py
npc_engine_import_wizard/import_wizards/hf_chatbot_import_wizard.py
npc_engine_import_wizard/import_wizards/hf_classifier_import_wizard.py
npc_engine_import_wizard/import_wizards/hf_similarity_import_wizard.py
npc_engine_import_wizard/import_wizards/flowtron_import_wizard/__init__.py
npc_engine_import_wizard/import_wizards/flowtron_import_wizard/flowtron_import_wizard.py
npc_engine_import_wizard/import_wizards/flowtron_import_wizard/flowtron_onnx.py
npc_engine_import_wizard-0.0.5.dist-info/LICENSE
npc_engine_import_wizard-0.0.5.dist-info/METADATA
npc_engine_import_wizard-0.0.5.dist-info/WHEEL
npc_engine_import_wizard-0.0.5.dist-info/entry_points.txt
npc_engine_import_wizard-0.0.5.dist-info/top_level.txt
npc_engine_import_wizard-0.0.5.dist-info/RECORD
