Metadata-Version: 2.1
Name: npc-engine-import-wizard
Version: 0.0.5
Summary: Import wizard for npc-engine
Home-page: https://github.com/npc-engine/npc-engine-import-wizard
Author: eublefar
Author-email: evil.unicorn1@gmail.com
License: MIT
Keywords: npc,AI,inference,deep-learning
Classifier: Development Status :: 3 - Alpha
Classifier: Topic :: Multimedia :: Sound/Audio :: Speech
Classifier: Intended Audience :: Developers
Classifier: Topic :: Scientific/Engineering :: Human Machine Interfaces
Classifier: Operating System :: Microsoft :: Windows
Classifier: Topic :: Software Development :: Libraries
Classifier: License :: OSI Approved :: MIT License
Classifier: Programming Language :: Python :: 3.7
Classifier: Programming Language :: Python :: 3.8
Requires-Python: >=3.7.0
License-File: LICENSE
Requires-Dist: npc-engine[cpu] (<1.0.0,>=0.0.1)
Provides-Extra: all
Requires-Dist: torch (<2.0.0,>=1.0.0) ; extra == 'all'
Requires-Dist: tensorboardX ; extra == 'all'
Requires-Dist: transformers (<5.0.0,>=4.0.0) ; extra == 'all'
Requires-Dist: espnet ; extra == 'all'
Provides-Extra: dev
Requires-Dist: pip-check-reqs (<3,>=2.0.1) ; extra == 'dev'
Requires-Dist: black (>=19.10b0) ; extra == 'dev'
Requires-Dist: flake8 (<4,>=3.7.9) ; extra == 'dev'
Requires-Dist: flake8-docstrings (<2,>=1.5.0) ; extra == 'dev'
Requires-Dist: pytest (>=6.0.1) ; extra == 'dev'
Requires-Dist: pytest-cov (<3,>=2.5.1) ; extra == 'dev'
Requires-Dist: pytest-pythonpath (<1,>=0.7.2) ; extra == 'dev'
Requires-Dist: setuptools (>=38.4.0) ; extra == 'dev'
Requires-Dist: tox (<4,>=3.0.0) ; extra == 'dev'
Requires-Dist: twine (==3.2.0) ; extra == 'dev'
Provides-Extra: espnet
Requires-Dist: torch (<2.0.0,>=1.0.0) ; extra == 'espnet'
Requires-Dist: espnet ; extra == 'espnet'
Provides-Extra: flowtron-tts
Requires-Dist: torch (<2.0.0,>=1.0.0) ; extra == 'flowtron-tts'
Requires-Dist: tensorboardX ; extra == 'flowtron-tts'
Provides-Extra: transformers
Requires-Dist: torch (<2.0.0,>=1.0.0) ; extra == 'transformers'
Requires-Dist: transformers (<5.0.0,>=4.0.0) ; extra == 'transformers'
